airflow/providers/jdbc/__init__.py
airflow/providers/jdbc/get_provider_info.py
airflow/providers/jdbc/hooks/__init__.py
airflow/providers/jdbc/hooks/jdbc.py
apache_airflow_providers_jdbc-5.3.2.dist-info/entry_points.txt
apache_airflow_providers_jdbc-5.3.2.dist-info/licenses/LICENSE
apache_airflow_providers_jdbc-5.3.2.dist-info/licenses/NOTICE
apache_airflow_providers_jdbc-5.3.2.dist-info/WHEEL
apache_airflow_providers_jdbc-5.3.2.dist-info/METADATA
apache_airflow_providers_jdbc-5.3.2.dist-info/RECORD
